{
  "status": "completed",
  "outcome": "werewolf_win",
  "winner_team": "werewolf_team",
  "winners": [
    "Twister",
    "EasyBake"
  ],
  "reason": "No werewolf was executed.",
  "executed": [
    "SafetySam",
    "Blaze",
    "ConspiBro"
  ],
  "werewolves_in_play": [
    "EasyBake"
  ],
  "executed_werewolves": [],
  "votes": {
    "Blaze": "SafetySam",
    "SafetySam": "Blaze",
    "Dr. Pizza": "Blaze",
    "Twister": "ConspiBro",
    "EasyBake": "ConspiBro",
    "ConspiBro": "SafetySam"
  },
  "tally": {
    "SafetySam": 2,
    "Blaze": 2,
    "ConspiBro": 2
  },
  "final_roles": {
    "Blaze": {
      "initial_role": "Tanner (皮匠)",
      "current_role": "Villager (村民)",
      "team": "village_team"
    },
    "SafetySam": {
      "initial_role": "Troublemaker (搗蛋鬼)",
      "current_role": "Troublemaker (搗蛋鬼)",
      "team": "village_team"
    },
    "Dr. Pizza": {
      "initial_role": "Villager (村民)",
      "current_role": "Tanner (皮匠)",
      "team": "tanner"
    },
    "Twister": {
      "initial_role": "Minion (爪牙)",
      "current_role": "Minion (爪牙)",
      "team": "werewolf_team"
    },
    "EasyBake": {
      "initial_role": "Werewolf (狼人)",
      "current_role": "Werewolf (狼人)",
      "team": "werewolf_team"
    },
    "ConspiBro": {
      "initial_role": "Villager (村民)",
      "current_role": "Villager (村民)",
      "team": "village_team"
    }
  },
  "game_id": "game_000024"
}